<level texture='monstersheet1'>
<sprite type = 'Hero.HeroSprite' x='55' y='40'/>
<sprite type = 'Bullet.BulletSprite' x='0' y='0' width='10' height='10' angle='0' restitution='0.5' static='false' friction='0.5' density='3' spawnEvent='onShoot'/>

<!-- BEGIN Monster construction -->
<sprite _label="brick" _color="0x00ff55" visual="rect.png" type="Beam.BeamSprite" controll_level="6" x="668" y="59" width="78" height="111" angle="0" restitution="0.2" static="true" friction="0.5" density="5" setName="Sprite_6"/>
<sprite _label="brick" _color="0x00ff55" visual="rect.png" type="Beam.BeamSprite" controll_level="6" x="975" y="188" width="71" height="102" angle="0" restitution="0.2" static="true" friction="0.5" density="5" setName="Sprite_6"/>
<sprite _label="brick" _color="0x00ff55" visual="rect.png" type="Beam.BeamSprite" controll_level="6" x="667" y="316" width="78" height="111" angle="0" restitution="0.2" static="true" friction="0.5" density="5" setName="Sprite_6"/>
<sprite _label="bar_long" _color="0x00ff55" visual="bar_long.png" type="Beam.BeamSprite" controll_level="6" x="819" y="381" width="383" height="23" angle="0" restitution="0.2" static="true" friction="0.5" density="5" firstframe="bar_long.png"/>
<sprite _label="bar_long" _color="0x00ff55" visual="bar_long.png" type="Beam.BeamSprite" controll_level="6" x="820" y="126" width="383" height="23" angle="0" restitution="0.2" static="true" friction="0.5" density="5" firstframe="bar_long.png"/>
<sprite _label="bar_long" _color="0x00ff55" visual="bar_long.png" type="Beam.BeamSprite" controll_level="6" x="821" y="249" width="496" height="25" angle="0" restitution="0.2" static="true" friction="0.5" density="5" firstframe="bar_long.png"/>
<sprite visual="boulder.png" type="Friend.FriendSprite" controll_level="5" x="794" y="187" width="89" height="89" angle="0" restitution="0.2" static="false" friction="0.5" density="1" firstframe="boulder.png"/>
<sprite _label="spinner" _color="0xff0000" visual="lovable_alien.png" type="Enemy.EnemySprite" controll_level="5" x="890" y="188" width="97" height="97" angle="0" restitution="0.2" static="false" friction="0.5" density="5" classname="LoveAlienSprite" firstframe="lovable_alien.png"/>
<sprite _label="spinner" _color="0xff0000" visual="lovable_alien.png" type="Enemy.EnemySprite" controll_level="5" x="899" y="314" width="97" height="97" angle="0" restitution="0.2" static="false" friction="0.5" density="5" classname="LoveAlienSprite" firstframe="lovable_alien.png"/>
<sprite _label="spinner" _color="0xff0000" visual="lovable_alien.png" type="Enemy.EnemySprite" controll_level="5" x="846" y="57" width="97" height="97" angle="0" restitution="0.2" static="false" friction="0.5" density="5" classname="LoveAlienSprite" firstframe="lovable_alien.png"/>
<sprite _label="ammo" _color="0xffff00" visual="crate.png" type="Crate.CrateSprite" controll_level="4" x="729" y="343" width="32" height="32" static="false" angle="0"/>
<sprite _label="ammo" _color="0xffff00" visual="crate.png" type="Crate.CrateSprite" controll_level="4" x="771" y="343" width="32" height="32" static="false" angle="0"/>
<sprite _label="ammo" _color="0xffff00" visual="crate.png" type="Crate.CrateSprite" controll_level="4" x="729" y="290" width="32" height="32" static="false" angle="0"/>
<sprite _label="ammo" _color="0xffff00" visual="crate.png" type="Crate.CrateSprite" controll_level="4" x="769" y="288" width="32" height="32" static="false" angle="0"/>
<sprite _label="medical" _color="0xffff00" visual="medical.png" type="Pickup.PickupSprite" controll_level="4" x="727" y="44" width="32" height="32" static="false" angle="0"/>
<sprite _label="medical" _color="0xffff00" visual="medical.png" type="Pickup.PickupSprite" controll_level="4" x="728" y="90" width="32" height="32" static="false" angle="0"/>
<sprite _label="brtittle" _color="0x00ff55" visual="brittle_brick.png" type="Beam.BeamSprite" controll_level="6" x="658" y="188" width="57" height="98" angle="0" restitution="0.2" static="true" friction="0.5" density="20" classname="Destructable" firstframe="rect.png" setName="dBeam"/>
<sprite _label="brtittle" _color="0x00ff55" visual="brittle_brick.png" type="Beam.BeamSprite" controll_level="6" x="984" y="315" width="57" height="105" angle="0" restitution="0.2" static="true" friction="0.5" density="20" classname="Destructable" firstframe="rect.png" setName="dBeam"/>
<sprite _label="brtittle" _color="0x00ff55" visual="brittle_brick.png" type="Beam.BeamSprite" controll_level="6" x="982" y="57" width="57" height="109" angle="0" restitution="0.2" static="true" friction="0.5" density="20" classname="Destructable" firstframe="rect.png" setName="dBeam"/>
<sprite _label="bar_long" _color="0x00ff55" visual="bar_long.png" type="Beam.BeamSprite" controll_level="6" x="451" y="5" width="378" height="27" angle="5" restitution="0.2" static="true" friction="0.5" density="5" firstframe="bar_long.png"/>
<sprite _label="brick" _color="0x00ff55" visual="rect.png" type="Beam.BeamSprite" controll_level="6" x="1691" y="498" width="36" height="36" angle="-45" restitution="0.2" static="true" friction="0.5" density="5" setName="Sprite_6"/>
<sprite visual="boulder.png" type="Friend.FriendSprite" controll_level="5" x="1706" y="70" width="89" height="89" angle="0" restitution="0.2" static="false" friction="0.5" density="1" firstframe="boulder.png" setName="Sprite_15"/>
<joint type="Joints.DistanceJoint" id="16" body1="Sprite_15" body2="Sprite_6" damping="0.2" freq="20" texture_type="line" texture="rect.png" texture_width="20" b1_Xoffset="1" b1_Yoffset="31" b2_Xoffset="1" b2_Yoffset="-10" bx="1692" by="488" ax="1707" ay="101"/>
<!-- END Monster construction -->

<sprite type="Teleporter.TeleporterSprite" level_id="leveldata/level_1_8_2"/>
</level>